Metadata-Version: 2.1
Name: imgbeddings
Version: 0.1.0
Summary: A Python package to generate image embeddings with CLIP without PyTorch/TensorFlow
Home-page: https://github.com/minimaxir/imgbeddings
Author: Max Woolf
Author-email: max@minimaxir.com
License: MIT
Keywords: ai,transformers,onnx,images,image-processing,embeddings,clip
Platform: UNKNOWN
Requires-Python: >=3.7
License-File: LICENSE
